cloudflareai/__init__.py
cloudflareai/core.py
cloudflareai/enums.py
cloudflareai/exceptions.py
cloudflareai/http.py
cloudflareai/models.py
cloudflareai/types.py
cloudflareai/ext/__init__.py
cloudflareai/ext/enums.py
cloudflareai-0.9.0.dist-info/LICENSE
cloudflareai-0.9.0.dist-info/METADATA
cloudflareai-0.9.0.dist-info/WHEEL
cloudflareai-0.9.0.dist-info/top_level.txt
cloudflareai-0.9.0.dist-info/RECORD
