Metadata-Version: 2.1
Name: cloudflareai
Version: 0.9.0
Summary: Cloudflare AI Python SDK
Home-page: https://github.com/alexraskin/cloudflareai-py
Author: alexraskin
Author-email: <root@alexraskin.com>
License: Mozilla Public License 2.0
Keywords: module,Cloudflare,library,package,python,CloudflareAI
Classifier: Programming Language :: Python
Classifier: Programming Language :: Python :: 3.11
License-File: LICENSE
Requires-Dist: httpx
